[
    {
    "image" : "https://zeushahn.github.io/Test/images/mov01.jpg",
    "title" : "토이스토리 4"
    },
    {
    "image" : "https://zeushahn.github.io/Test/images/mov02.jpg",
    "title" : "호빗"
    },
    {
    "image" : "https://zeushahn.github.io/Test/images/mov03.jpg",
    "title" : "제이슨 본"
    },
    {
    "image" : "https://zeushahn.github.io/Test/images/mov04.jpg",
    "title" : "반지의 제왕"
    },
    {
    "image" : "https://zeushahn.github.io/Test/images/mov05.jpg",
    "title" : "정직한 후보"
    },
    {
    "image" : "https://zeushahn.github.io/Test/images/mov06.jpg",
    "title" : "나쁜 녀석들"
    },
    {
    "image" : "https://zeushahn.github.io/Test/images/mov07.jpg",
    "title" : "겨울 왕국 2"
    },
    {
    "image" : "https://zeushahn.github.io/Test/images/mov08.jpg",
    "title" : "알리딘"
    },
    {
    "image" : "https://zeushahn.github.io/Test/images/mov09.jpg",
    "title" : "극한직업"
    },
    {
    "image" : "https://zeushahn.github.io/Test/images/mov10.jpg", 
    "title" : "스파이더맨"
    }
]
